{
    "template": "Each Sales Representatives has many different Territories. Among them, Region is common to many Sales Representatives.",
    "entities": {
        "tab_name": "Sales_Representatives",
        "col_name": null,
        "value": null,
        "scope_id": null,
        "db_type": "table"
    },
    "components": {
        "tab_name": "Territories",
        "col_name": null,
        "value": null,
        "scope_id": null,
        "db_type": "table"
    },
    "specific_component": {
        "tab_name": "Territories",
        "col_name": "Name",
        "value": "Central Region",
        "scope_id": 2,
        "db_type": "value"
    },
    "entities_components": {
        "tab_name": "Sales_Representatives_Territories",
        "col_name": null,
        "value": null,
        "scope_id": null,
        "db_type": "table"
    }
}