{
    "template": "Question: Who designed this intersection? Subject of Inquiry: Intersection\nFocus: Designer Possible answer types: 1. Civil Engineer 2. Engineering Firm",
    "general_category1": {
        "tab_name": "CivilEngineers",
        "col_name": "Civil_Engineer",
        "value": null,
        "scope_id": null,
        "db_type": "column"
    },
    "general_category2": {
        "tab_name": "CivilEngineers",
        "col_name": "Engineering_Firm",
        "value": null,
        "scope_id": null,
        "db_type": "column"
    },
    "subject": {
        "tab_name": "CivilEngineers",
        "col_name": "Intersection",
        "value": null,
        "scope_id": null,
        "db_type": "column"
    },
    "type": "2cols"
}