{
    "template": "Each Law Firms has many different Legal Positions. Among them, Paralegal is common to many Law Firms.",
    "entities": {
        "tab_name": "Law_Firms",
        "col_name": null,
        "value": null,
        "scope_id": null,
        "db_type": "table"
    },
    "components": {
        "tab_name": "Legal_Positions",
        "col_name": null,
        "value": null,
        "scope_id": null,
        "db_type": "table"
    },
    "specific_component": {
        "tab_name": "Legal_Positions",
        "col_name": "position_name",
        "value": "Paralegal",
        "scope_id": 0,
        "db_type": "value"
    },
    "entities_components": {
        "tab_name": "Law_Firms_Legal_Positions",
        "col_name": null,
        "value": null,
        "scope_id": null,
        "db_type": "table"
    }
}